Metadata-Version: 2.1
Name: aakbar
Version: 0.17
Summary:  aakbar -- amino-acid k-mer signature tools 
Home-page: http://github.com/ncgr/aakbar
Author: Joel Berendzen
Author-email: joelb@ncgr.org
Maintainer: Joel Berendzen
Maintainer-email: joelb@ncgr.org
License: BSD 3-Clause License
Keywords: science,biology,bioinformatics,genomics,statistics,peptide,signatures,DNA,protein,sequence,complexity,simplicity,alignment,genes,gene families
Platform: UNKNOWN
Classifier: Development Status :: 5 - Production/Stable
Classifier: Environment :: Console
Classifier: Intended Audience :: Science/Research
Classifier: License :: OSI Approved :: BSD License
Classifier: Natural Language :: English
Classifier: Operating System :: OS Independent
Classifier: Programming Language :: Python :: 3.4
Classifier: Programming Language :: Python :: 3.5
Classifier: Programming Language :: Python :: 3.6
Classifier: Programming Language :: Python :: 3.7
Classifier: Topic :: Scientific/Engineering :: Bio-Informatics
Provides-Extra: docs
Provides-Extra: tests
Provides-Extra: all
